pyqtexcept_forgenet/__init__.py
pyqtexcept_forgenet/main.py
pyqtexcept-0.0.1.dist-info/LICENSE
pyqtexcept-0.0.1.dist-info/METADATA
pyqtexcept-0.0.1.dist-info/WHEEL
pyqtexcept-0.0.1.dist-info/top_level.txt
pyqtexcept-0.0.1.dist-info/RECORD
