Metadata-Version: 2.1
Name: pyqtexcept
Version: 0.0.1
Summary: Exception handling for PyQt5 applications
Author-email: Forgenet <forgenet@inbox.ru>
Project-URL: Homepage, https://github.com/f0rgenet/pyqtexcept
Classifier: Programming Language :: Python :: 3
Classifier: License :: OSI Approved :: MIT License
Classifier: Operating System :: OS Independent
Requires-Python: >=3.6
License-File: LICENSE
